installPhdl/PhotoLibDownloader-0.8.14-py3-none-any.whl
installPhdl/__init__.py
installPhdl/__main__.py
installPhdl/installPhdl.py
installPhdl-0.8.14.dist-info/LICENSE.md
installPhdl-0.8.14.dist-info/METADATA
installPhdl-0.8.14.dist-info/WHEEL
installPhdl-0.8.14.dist-info/entry_points.txt
installPhdl-0.8.14.dist-info/top_level.txt
installPhdl-0.8.14.dist-info/RECORD
