Metadata-Version: 2.1
Name: installPhdl
Version: 0.8.14
Summary: Install PhotoLibDownloader GUI
Author-email: MrChad <mrchad0815@icloud.com>
License: MIT
Requires-Python: >=3.9
License-File: LICENSE.md
Requires-Dist: pyinstaller >=5.13.2
